fast_xid/__init__.py
fast_xid-0.1.0.dist-info/METADATA
fast_xid-0.1.0.dist-info/WHEEL
fast_xid-0.1.0.dist-info/RECORD
