Metadata-Version: 2.1
Name: fast-xid
Version: 0.1.0
Summary: 
Author: Chongchen Chen
Author-email: chenkovsky@qq.com
Requires-Python: >=3.11
Classifier: Programming Language :: Python :: 3
Classifier: Programming Language :: Python :: 3.11
Classifier: Programming Language :: Python :: 3.12
Requires-Dist: rsatomic (>=0.1.0,<0.2.0)
